tests/__init__.py
tests/requirements.txt
tests/test1.py
vohlc/__init__.py
vohlc/client.py
vohlc/base/__init__.py
vohlc/base/collect_data.py
vohlc/base/transform_ohlcv.py
vohlc-0.1.0.dist-info/LICENSE
vohlc-0.1.0.dist-info/METADATA
vohlc-0.1.0.dist-info/WHEEL
vohlc-0.1.0.dist-info/top_level.txt
vohlc-0.1.0.dist-info/zip-safe
vohlc-0.1.0.dist-info/RECORD
