Metadata-Version: 2.1
Name: vohlc
Version: 0.1.0
Summary: Create Candlestick data based on volume instead of time
Home-page: https://github.com/paulschick/python-vohlc
Author: Paul Schick
Author-email: paul@paulschick.dev
License: MIT
Platform: UNKNOWN
License-File: LICENSE
Requires-Dist: ccxt
Requires-Dist: pandas
